LICENSE
MANIFEST.in
README.rst
requirements.txt
setup.cfg
setup.py
ckanext/__init__.py
ckanext/odi_certificates_client/__init__.py
ckanext/odi_certificates_client/plugin.py
ckanext/odi_certificates_client/lib/__init__.py
ckanext/odi_certificates_client/lib/request.py
ckanext/odi_certificates_client/logic/__init__.py
ckanext/odi_certificates_client/logic/action/__init__.py
ckanext/odi_certificates_client/logic/action/get.py
ckanext/odi_certificates_client/logic/auth/__init__.py
ckanext/odi_certificates_client/logic/auth/get.py
ckanext/odi_certificates_client/tests/__init__.py
ckanext/odi_certificates_client/tests/test_plugin.py
ckanext_odi_certificates_client.egg-info/PKG-INFO
ckanext_odi_certificates_client.egg-info/SOURCES.txt
ckanext_odi_certificates_client.egg-info/dependency_links.txt
ckanext_odi_certificates_client.egg-info/entry_points.txt
ckanext_odi_certificates_client.egg-info/namespace_packages.txt
ckanext_odi_certificates_client.egg-info/top_level.txt