Metadata-Version: 1.1
Name: ckanext-odi-certificates-client
Version: 1.0.0
Summary: A client for open data certificate server.
Home-page: https://github.com/mattRedBox/ckanext-odi_certificates_client
Author: mattRedBox
Author-email: matt@redboxresearchdata.com.au
License: AGPL
Keywords: CKAN ODI-Queensland QCIF certificates open-data-certificate
Platform: UNKNOWN
Classifier: Development Status :: 4 - Beta
Classifier: License :: OSI Approved :: GNU Affero General Public License v3 or later (AGPLv3+)
Classifier: Programming Language :: Python :: 2.7
